kospellcheck/__init__.py
kospellcheck/checker.py
ko_spell_check-1.0.3.dist-info/LICENSE
ko_spell_check-1.0.3.dist-info/METADATA
ko_spell_check-1.0.3.dist-info/WHEEL
ko_spell_check-1.0.3.dist-info/top_level.txt
ko_spell_check-1.0.3.dist-info/RECORD
