Metadata-Version: 2.1
Name: ko-spell-check
Version: 1.0.3
Summary: A Python package for Korean spell checking using Naver API
Home-page: https://github.com/yourusername/ko-spell-check
Author: Your Name
Author-email: your.email@example.com
Classifier: Programming Language :: Python :: 3
Classifier: License :: OSI Approved :: MIT License
Classifier: Operating System :: OS Independent
Requires-Python: >=3.7
License-File: LICENSE
Requires-Dist: requests
